[
    {
        "icon": "img/advantages/advantages1.svg",
        "head": "Часы работы:",
        "text": "с 7:00 до 19:00"
    },
    {
        "icon": "img/advantages/advantages2.svg",
        "head": "Группы:",
        "text": "до 15 человек"
    },
    {
        "icon": "img/advantages/advantages3.svg",
        "head": "Площадь для прогулок:",
        "text": "собственная оборудованная территория для прогулок"
    },
    {
        "icon": "img/advantages/advantages4.svg",
        "head": "Видеонаблюдение:",
        "text": "24/7"
    },
    {
        "icon": "img/advantages/advantages5.svg",
        "head": "Занятия английским языком с педагогом:",
        "text": "ежедневно"
    },
    {
        "icon": "img/advantages/advantages6.svg",
        "head": "Возраст детей:",
        "text": "от 1 до 7 лет"
    },
    {
        "icon": "img/advantages/advantages7.svg",
        "head": "Утренний фильтр:",
        "text": "ежедневно"
    },
    {
        "icon": "img/advantages/advantages8.svg",
        "head": "Помещение:",
        "text": "800 кв.м"
    },
    {
        "icon": "img/advantages/advantages9.svg",
        "head": "Питание:",
        "text": "5-разовое, с учетом индивидуальных особенностей ребенка"
    }
]
